Technology/__init__.py
Technology/math.py
Technology/password.py
Technology/spider.py
Technology/GhRobot/Bot.py
Technology/GhRobot/Code.py
Technology/GhRobot/Follow.py
Technology/GhRobot/Search.py
Technology/GhRobot/ToCsv.py
Technology/GhRobot/Tool.py
Technology/GhRobot/User.py
Technology/GhRobot/__init__.py
Technology_Note-0.1.0.dist-info/LICENSE
Technology_Note-0.1.0.dist-info/METADATA
Technology_Note-0.1.0.dist-info/WHEEL
Technology_Note-0.1.0.dist-info/top_level.txt
Technology_Note-0.1.0.dist-info/RECORD
