Metadata-Version: 2.1
Name: Technology-Note
Version: 0.1.0
Summary: Learn the techniques developed in Python
Home-page: https://github.com/CoolPlayLin/Technology-Note/
Download-URL: https://github.com/CoolPlayLin/Technology-Note/releases
Author: CoolPlayLin
Author-email: help@api-coolplaylin.eu.org
Project-URL: Bug Report, https://github.com/CoolPlayLin/Technology-Note/issues/new
Project-URL: Feature Request, https://github.com/CoolPlayLin/Technology-Note/issues/new
Classifier: Development Status :: 2 - Pre-Alpha
Classifier: Natural Language :: English
Classifier: Programming Language :: Python :: 3.6
Classifier: Programming Language :: Python :: 3.7
Classifier: Programming Language :: Python :: 3.8
Classifier: Programming Language :: Python :: 3.9
Classifier: Programming Language :: Python :: 3.10
Classifier: Programming Language :: Python :: 3.11
Classifier: Topic :: Software Development :: Libraries :: Python Modules
Classifier: License :: OSI Approved :: MIT License
Requires: requests
License-File: LICENSE
